{
    "os_list": [
        {
            "name": "Fedora Asahi Remix 40 with KDE Plasma",
            "default_os_name": "Fedora Linux with KDE Plasma",
            "boot_object": "m1n1.bin",
            "next_object": "m1n1/boot.bin",
            "package": "https://asahilinux-fedora.b-cdn.net/os/fedora-40-kde-202410071603.zip",
            "icon": "fedora.icns",
            "supported_fw": [
                "12.3",
                "12.3.1",
                "13.5"
            ],
            "extras": [
                "https://codecs.fedoraproject.org/openh264/40/aarch64/os/Packages/m/mozilla-openh264-2.4.1-2.fc40.aarch64.rpm",
                "https://codecs.fedoraproject.org/openh264/40/aarch64/os/Packages/o/openh264-2.4.1-2.fc40.aarch64.rpm"
            ],
            "partitions": [
                {
                    "name": "EFI",
                    "type": "EFI",
                    "size": "524288000B",
                    "format": "fat",
                    "volume_id": "0x9d773f46",
                    "copy_firmware": true,
                    "copy_installer_data": true,
                    "source": "esp"
                },
                {
                    "name": "Boot",
                    "type": "Linux",
                    "size": "1073741824B",
                    "image": "boot.img"
                },
                {
                    "name": "Root",
                    "type": "Linux",
                    "size": "14510174208B",
                    "expand": true,
                    "image": "root.img"
                }
            ]
        },
        {
            "name": "Fedora Asahi Remix 40 with GNOME",
            "default_os_name": "Fedora Linux with GNOME",
            "boot_object": "m1n1.bin",
            "next_object": "m1n1/boot.bin",
            "package": "https://asahilinux-fedora.b-cdn.net/os/fedora-40-gnome-202410071603.zip",
            "icon": "fedora.icns",
            "supported_fw": [
                "12.3",
                "12.3.1",
                "13.5"
            ],
            "extras": [
                "https://codecs.fedoraproject.org/openh264/40/aarch64/os/Packages/m/mozilla-openh264-2.4.1-2.fc40.aarch64.rpm",
                "https://codecs.fedoraproject.org/openh264/40/aarch64/os/Packages/o/openh264-2.4.1-2.fc40.aarch64.rpm"
            ],
            "partitions": [
                {
                    "name": "EFI",
                    "type": "EFI",
                    "size": "524288000B",
                    "format": "fat",
                    "volume_id": "0xa4805400",
                    "copy_firmware": true,
                    "copy_installer_data": true,
                    "source": "esp"
                },
                {
                    "name": "Boot",
                    "type": "Linux",
                    "size": "1073741824B",
                    "image": "boot.img"
                },
                {
                    "name": "Root",
                    "type": "Linux",
                    "size": "11628687360B",
                    "expand": true,
                    "image": "root.img"
                }
            ]
        },
        {
            "name": "Fedora Asahi Remix 40 Server",
            "default_os_name": "Fedora Linux Server",
            "boot_object": "m1n1.bin",
            "next_object": "m1n1/boot.bin",
            "package": "https://asahilinux-fedora.b-cdn.net/os/fedora-40-server-202410071603.zip",
            "icon": "fedora.icns",
            "supported_fw": [
                "12.3",
                "12.3.1",
                "13.5"
            ],
            "extras": {},
            "partitions": [
                {
                    "name": "EFI",
                    "type": "EFI",
                    "size": "524288000B",
                    "format": "fat",
                    "volume_id": "0x88d3c992",
                    "copy_firmware": true,
                    "copy_installer_data": true,
                    "source": "esp"
                },
                {
                    "name": "Boot",
                    "type": "Linux",
                    "size": "1073741824B",
                    "image": "boot.img"
                },
                {
                    "name": "Root",
                    "type": "Linux",
                    "size": "4575965184B",
                    "expand": true,
                    "image": "root.img"
                }
            ]
        },
        {
            "name": "Fedora Asahi Remix 40 Minimal",
            "default_os_name": "Fedora Linux Minimal",
            "boot_object": "m1n1.bin",
            "next_object": "m1n1/boot.bin",
            "package": "https://asahilinux-fedora.b-cdn.net/os/fedora-40-minimal-202410071603.zip",
            "icon": "fedora.icns",
            "supported_fw": [
                "12.3",
                "12.3.1",
                "13.5"
            ],
            "extras": {},
            "partitions": [
                {
                    "name": "EFI",
                    "type": "EFI",
                    "size": "524288000B",
                    "format": "fat",
                    "volume_id": "0x8293a8b7",
                    "copy_firmware": true,
                    "copy_installer_data": true,
                    "source": "esp"
                },
                {
                    "name": "Boot",
                    "type": "Linux",
                    "size": "1073741824B",
                    "image": "boot.img"
                },
                {
                    "name": "Root",
                    "type": "Linux",
                    "size": "4053774336B",
                    "expand": true,
                    "image": "root.img"
                }
            ]
        },
        {
            "name": "Arch Linux ARM (not recommended)",
            "default_os_name": "Arch Linux ARM",
            "expert": true,
            "boot_object": "m1n1.bin",
            "next_object": "m1n1/boot.bin",
            "package": "asahi-base-20231012-1.zip",
            "supported_fw": [
                "12.3",
                "12.3.1",
                "13.5"
            ],
            "partitions": [
                {
                    "name": "EFI",
                    "type": "EFI",
                    "size": "500MB",
                    "format": "fat",
                    "volume_id": "0x2abf9f91",
                    "copy_firmware": true,
                    "copy_installer_data": true,
                    "source": "esp"
                },
                {
                    "name": "Root",
                    "type": "Linux",
                    "size": "5GB",
                    "expand": true,
                    "image": "root.img"
                }
            ]
        },
        {
            "name": "UEFI environment only (m1n1 + U-Boot + ESP)",
            "default_os_name": "UEFI boot",
            "boot_object": "m1n1.bin",
            "next_object": "m1n1/boot.bin",
            "package": "uefi-only-20231220-1.zip",
            "supported_fw": [
                "12.3",
                "12.3.1",
                "13.5"
            ],
            "partitions": [
                {
                    "name": "EFI",
                    "type": "EFI",
                    "size": "500MB",
                    "format": "fat",
                    "copy_firmware": true,
                    "copy_installer_data": true,
                    "source": "esp"
                }
            ]
        },
        {
            "name": "Tethered boot (m1n1, for development)",
            "default_os_name": "m1n1 proxy",
            "expert": true,
            "boot_object": "m1n1.bin",
            "external_boot": true,
            "partitions": []
        }
    ]
}
